linux/__init__.py
linux/logs_reporting.py
linux/network_con.py
linux/network_interface.py
linux/packets.py
linux/portscan.py
linux/security.py
linux/speedtest.py
linux/wifianalysis.py
windows/__init__.py
windows/logs_reporting.py
windows/network_con.py
windows/network_interface.py
windows/packets.py
windows/portscan.py
windows/security.py
windows/speedtest.py
windows/wifianalysis.py
NetDiagnose-1.0.1.dist-info/LICENSE
NetDiagnose-1.0.1.dist-info/METADATA
NetDiagnose-1.0.1.dist-info/WHEEL
NetDiagnose-1.0.1.dist-info/entry_points.txt
NetDiagnose-1.0.1.dist-info/top_level.txt
NetDiagnose-1.0.1.dist-info/RECORD
