Metadata-Version: 2.1
Name: NetDiagnose
Version: 1.0.1
Summary: A network diagnostic assistant
Home-page: https://github.com/gentlsnek/NetDiagnose
Author: Erwin Pimenta
Author-email: erwinpimenta1644@gmail.com
Classifier: Programming Language :: Python :: 3
Classifier: License :: OSI Approved :: MIT License
Classifier: Operating System :: OS Independent
Requires-Python: >=3.6
License-File: LICENSE
Requires-Dist: customtkinter
Requires-Dist: scapy
Requires-Dist: psutil
Requires-Dist: speedtest-cli
Requires-Dist: ping3
